MANIFEST.in
README.rst
requirements.txt
setup.cfg
setup.py
djmicrosip_inventarios/__init__.py
djmicrosip_inventarios/__init__.pyc
djmicrosip_inventarios/autocomplete_light_registry.pyc
djmicrosip_inventarios/config.pyc
djmicrosip_inventarios/models.pyc
djmicrosip_inventarios/tests.pyc
djmicrosip_inventarios/urls.pyc
djmicrosip_inventarios/views.pyc
djmicrosip_inventarios.egg-info/PKG-INFO
djmicrosip_inventarios.egg-info/SOURCES.txt
djmicrosip_inventarios.egg-info/dependency_links.txt
djmicrosip_inventarios.egg-info/requires.txt
djmicrosip_inventarios.egg-info/top_level.txt
djmicrosip_inventarios/almacenes/__init__.py
djmicrosip_inventarios/almacenes/__init__.pyc
djmicrosip_inventarios/almacenes/forms.pyc
djmicrosip_inventarios/almacenes/models.pyc
djmicrosip_inventarios/almacenes/urls.pyc
djmicrosip_inventarios/almacenes/views.pyc
djmicrosip_inventarios/core/__init__.py
djmicrosip_inventarios/core/__init__.pyc
djmicrosip_inventarios/core/models.pyc
djmicrosip_inventarios/core/urls.pyc
djmicrosip_inventarios/core/views.pyc
djmicrosip_inventarios/herramientas/__init__.py
djmicrosip_inventarios/herramientas/__init__.pyc
djmicrosip_inventarios/herramientas/forms.pyc
djmicrosip_inventarios/herramientas/report_builder.py
djmicrosip_inventarios/herramientas/report_builder.pyc
djmicrosip_inventarios/herramientas/urls.pyc
djmicrosip_inventarios/herramientas/views.pyc
djmicrosip_inventarios/inventarios_fisicos/__init__.py
djmicrosip_inventarios/inventarios_fisicos/__init__.pyc
djmicrosip_inventarios/inventarios_fisicos/forms.pyc
djmicrosip_inventarios/inventarios_fisicos/models.pyc
djmicrosip_inventarios/inventarios_fisicos/urls.pyc
djmicrosip_inventarios/inventarios_fisicos/views.pyc
djmicrosip_inventarios/static/djmicrosip_inventarios/css/styles.css
djmicrosip_inventarios/static/djmicrosip_inventarios/js/inventarios.articulo.clave.js
djmicrosip_inventarios/static/djmicrosip_inventarios/js/inventarios.articulo.js
djmicrosip_inventarios/static/djmicrosip_inventarios/js/inventarios.articulo.series.js
djmicrosip_inventarios/static/djmicrosip_inventarios/js/inventarios.herramientas.js
djmicrosip_inventarios/static/djmicrosip_inventarios/js/inventarios.manager.conteos.js
