Metadata-Version: 1.0
Name: djmicrosip-inventarios
Version: 1.2.3
Summary: django microsip inventarios fisicos
Home-page: UNKNOWN
Author: Servicios de Ingenieria Computacional
Author-email: desarrollo@siccomputacion.com
License: BSD License
Platform: UNKNOWN
Classifier: Environment :: Web Environment
Classifier: Framework :: Django
Classifier: Intended Audience :: Developers
Classifier: License :: OSI Approved :: BSD License
Classifier: Operating System :: OS Independent
Classifier: Programming Language :: Python
Classifier: Programming Language :: Python :: 2.6
Classifier: Programming Language :: Python :: 2.7
Classifier: Topic :: Internet :: WWW/HTTP
Classifier: Topic :: Internet :: WWW/HTTP :: Dynamic Content
